setup.py
distributions_aman/Binomialdistribution.py
distributions_aman/Gaussiandistribution.py
distributions_aman/Generaldistribution.py
distributions_aman/__init__.py
distributions_aman.egg-info/PKG-INFO
distributions_aman.egg-info/SOURCES.txt
distributions_aman.egg-info/dependency_links.txt
distributions_aman.egg-info/not-zip-safe
distributions_aman.egg-info/top_level.txt